mcitemlib/__init__.py
mcitemlib/itemlib.py
mcitemlib/legacy.py
mcitemlib/style.py
mcitemlib-0.5.2.dist-info/METADATA
mcitemlib-0.5.2.dist-info/WHEEL
mcitemlib-0.5.2.dist-info/licenses/LICENSE
mcitemlib-0.5.2.dist-info/RECORD
