Metadata-Version: 2.4
Name: mcitemlib
Version: 0.5.2
Summary: A library for creating and editing Minecraft items using python
License-Expression: MIT
License-File: LICENSE
Keywords: minecraft,item,block,nbt
Author: Amp
Requires-Python: >=3.10
Classifier: Programming Language :: Python :: 3
Classifier: Programming Language :: Python :: 3.10
Classifier: Programming Language :: Python :: 3.11
Classifier: Programming Language :: Python :: 3.12
Classifier: Programming Language :: Python :: 3.13
Classifier: Programming Language :: Python :: 3.14
Provides-Extra: dev
Requires-Dist: pytest (>=9.0.2) ; extra == "dev"
Requires-Dist: rapidnbt (>=1.3.3)
Requires-Dist: twine (>=6.2.0) ; extra == "dev"
Project-URL: Repository, https://github.com/Amp63/mcitemlib
